semivalues/__init__.py
semivalues/banzhaf.py
semivalues/shapley.py
semivalues/decompositions/__init__.py
semivalues/decompositions/by_size/__init__.py
semivalues/decompositions/by_size/banzhaf.py
semivalues/decompositions/by_size/shapley.py
semivalues/decompositions/player_to_player/__init__.py
semivalues/decompositions/player_to_player/shapley.py
semivalues/graphs/__init__.py
semivalues/graphs/utils.py
semivalues/graphs/connectivity_games/__init__.py
semivalues/graphs/connectivity_games/banzhaf.py
semivalues/graphs/connectivity_games/shapley.py
semivalues/graphs/connectivity_games/skibski_algorithm.py
semivalues/graphs/connectivity_games/decompositions/__init__.py
semivalues/graphs/connectivity_games/decompositions/skibski_algorithm.py
semivalues/graphs/connectivity_games/decompositions/banzhaf/__init__.py
semivalues/graphs/connectivity_games/decompositions/banzhaf/by_size.py
semivalues/graphs/connectivity_games/decompositions/shapley/__init__.py
semivalues/graphs/connectivity_games/decompositions/shapley/by_size.py
semivalues/utils/__init__.py
semivalues/utils/strata.py
semivalues/utils/weights.py
semivalues-0.0.16.dist-info/METADATA
semivalues-0.0.16.dist-info/WHEEL
semivalues-0.0.16.dist-info/licenses/LICENSE
semivalues-0.0.16.dist-info/RECORD
